[
    {
        "file": "chris.js",
        "output": false,
        "name": false,
        "id": false,
        "email": false,
        "language": false,
        "status": "Fail"
    },
    {
        "file": "hello.py",
        "output": "Hello World, this is Oluwafunmibi Adepoju with HNGi7 ID HNG-01478 using Python for stage 2 task",
        "name": "Oluwafunmibi Adepoju",
        "id": "HNG-01478",
        "email": "o.funmibi@gmail.com",
        "language": "Python",
        "status": "Pass"
    },
    {
        "file": "jeje.py",
        "output": "Hello World, this is Jeje Demi with HNGi7 ID HNG-01948, I am using Python for stage 2 task",
        "name": "Jeje Demi",
        "id": "HNG-01948",
        "email": "j.demi@yahoo.fr",
        "language": "Python",
        "status": "Fail"
    }
]